{"name":"A. Ярмарка","testType":"SINGLE","input":{"type":"STANDARD","fileName":"input.txt"},"output":{"type":"STANDARD","fileName":"output.txt"},"tests":[{"input":"5 5 4 3\n1 2 4 3 2\n1 2\n2 3\n3 4\n4 1\n4 5\n","output":"2 2 2 2 3\n","index":0,"active":true},{"input":"7 6 3 2\n1 2 3 3 2 2 1\n1 2\n2 3\n3 4\n2 5\n5 6\n6 7\n","output":"1 1 1 2 2 1 1\n","index":1,"active":true}],"location":"main/net/egork","vmArgs":"-Xmx512M -Xss8M","mainClass":"Main","taskClass":"net.egork.AJarmarka","checkerClass":"net.egork.chelper.checkers.TokenChecker","checkerParameters":"","testClasses":[],"date":"2018.05.29","contestName":"Codeforces Round #485 (Div. 1)","truncate":true,"inputClass":"net.egork.io.InputReader","outputClass":"net.egork.io.OutputWriter","includeLocale":false,"failOnOverflow":true}