{
  "name" : "A - Reorder the Array",
  "testType" : "SINGLE",
  "input" : {
    "type" : "STANDARD"
  },
  "output" : {
    "type" : "STANDARD"
  },
  "tests" : [ ],
  "location" : "main/net/egork",
  "vmArgs" : "-Xmx256M",
  "mainClass" : "Main",
  "taskClass" : "net.egork.TaskA",
  "checkerClass" : "net.egork.chelper.checkers.TokenChecker",
  "checkerParameters" : "",
  "testClasses" : [ ],
  "date" : "2018.07.13",
  "contestName" : "Codeforces Round #497 (Div. 1)",
  "truncate" : true,
  "inputClass" : "net.egork.io.InputReader",
  "outputClass" : "net.egork.io.OutputWriter",
  "includeLocale" : false,
  "failOnOverflow" : true,
  "interactive" : false
}